foto/__init__.py
foto/cli.py
foto/logger.py
foto/utils/__init__.py
foto/utils/creation_datetime.py
foto/utils/geo.py
foto/utils/metadata.py
foto-1.0.0.dist-info/DESCRIPTION.rst
foto-1.0.0.dist-info/METADATA
foto-1.0.0.dist-info/RECORD
foto-1.0.0.dist-info/WHEEL
foto-1.0.0.dist-info/entry_points.txt
foto-1.0.0.dist-info/metadata.json
foto-1.0.0.dist-info/top_level.txt
