Metadata-Version: 2.0
Name: foto
Version: 1.0.0
Summary: Command line photo manager
Home-page: https://github.com/honzajavorek/foto
Author: Honza Javorek
Author-email: mail@honzajavorek.cz
License: Copyright (c) 2010-?, Honza Javorek <mail@honzajavorek.cz>
Requires-Dist: arrow
Requires-Dist: click
Requires-Dist: colorama
Requires-Dist: geocoder
Requires-Dist: lxml
Requires-Dist: plumbum
Requires-Dist: pyaml
Requires-Dist: pync
Requires-Dist: python-slugify
Requires-Dist: send2trash
Provides-Extra: release
Requires-Dist: python-semantic-release; extra == 'release'
Provides-Extra: tests
Requires-Dist: coveralls; extra == 'tests'
Requires-Dist: flake8; extra == 'tests'
Requires-Dist: pytest; extra == 'tests'
Requires-Dist: pytest-cov; extra == 'tests'
Requires-Dist: pytest-runner; extra == 'tests'
